pyroarc/__init__.py
pyroarc/pyroarc.py
pyroarc/pyroarc_test.py
pyroarc-1.1.2.dist-info/LICENSE
pyroarc-1.1.2.dist-info/METADATA
pyroarc-1.1.2.dist-info/WHEEL
pyroarc-1.1.2.dist-info/top_level.txt
pyroarc-1.1.2.dist-info/RECORD
