Metadata-Version: 2.1
Name: pyroarc
Version: 1.1.2
Summary: This package performs transformation
Home-page: https://github.com/IE-Group-C/pyroar
Author: Group C
Author-email: ali.alhammad@student.ie.edu
License: UNKNOWN
Project-URL: Bug Tracker, https://github.com/IE-Group-C/pyroar/issues
Platform: UNKNOWN
Classifier: Programming Language :: Python :: 3
Classifier: License :: OSI Approved :: MIT License
Classifier: Operating System :: OS Independent
Requires-Python: >=3.6
License-File: LICENSE
